py_unsplash_source/__init__.py
py_unsplash_source/py_unsplash_source_client.py
py_unsplash_source/unsplash_endpoint.py
py_unsplash_source/getters/__init__.py
py_unsplash_source/getters/base_getter.py
py_unsplash_source/getters/reload_frequency.py
py_unsplash_source/getters/impl/__init__.py
py_unsplash_source/getters/impl/image_from_collection_getter.py
py_unsplash_source/getters/impl/image_from_featured_getter.py
py_unsplash_source/getters/impl/image_from_user_getter.py
py_unsplash_source/getters/impl/image_getter.py
py_unsplash_source/getters/impl/random_image_getter.py
py_unsplash_source/images/__init__.py
py_unsplash_source/images/fetched_image.py
tests/py_unsplash_source/__init__.py
tests/py_unsplash_source/test_py_unsplash_source_client.py
tests/py_unsplash_source/test_unsplash_endpoint.py
tests/py_unsplash_source/getters/__init__.py
tests/py_unsplash_source/getters/test_base_getter.py
tests/py_unsplash_source/getters/impl/__init__.py
tests/py_unsplash_source/getters/impl/test_image_from_collection_getter.py
tests/py_unsplash_source/getters/impl/test_image_from_featured_getter.py
tests/py_unsplash_source/getters/impl/test_image_from_user_getter.py
tests/py_unsplash_source/getters/impl/test_image_getter.py
tests/py_unsplash_source/getters/impl/test_random_image_getter.py
py_unsplash_source-0.9.0.dist-info/LICENSE
py_unsplash_source-0.9.0.dist-info/METADATA
py_unsplash_source-0.9.0.dist-info/WHEEL
py_unsplash_source-0.9.0.dist-info/top_level.txt
py_unsplash_source-0.9.0.dist-info/zip-safe
py_unsplash_source-0.9.0.dist-info/RECORD
