Metadata-Version: 2.1
Name: py-unsplash-source
Version: 0.9.0
Summary: Python library to get pictures from source.unsplash.com
Home-page: https://github.com/kromg/py-unsplash-source
Author: Giacomo Montagner
Author-email: kromg.kromg@gmail.com
License: GNU GENERAL PUBLIC LICENSE Version 3
Platform: POSIX
Requires-Dist: requests
